{
  "id": "1.13 Multiplayer",
  "title": "1.13 Multiplayer",
  "description": "Alliances",
  "source": "@site/docs/1.13 Multiplayer.md",
  "sourceDirName": ".",
  "slug": "/1.13 Multiplayer",
  "permalink": "/docs/1.13 Multiplayer",
  "draft": false,
  "unlisted": false,
  "editUrl": "https://github.com/facebook/docusaurus/tree/main/packages/create-docusaurus/templates/shared/docs/1.13 Multiplayer.md",
  "tags": [],
  "version": "current",
  "frontMatter": {},
  "sidebar": "tutorialSidebar",
  "previous": {
    "title": "Gaining Spells",
    "permalink": "/docs/1.12 Magic"
  },
  "next": {
    "title": "1.2 Turn Sequence",
    "permalink": "/docs/1.2 Turn Sequence"
  }
}